{"cameraMode":{"drawMode":0,"name":"Shaded","section":"Shading Mode"},"sceneLighting":false,"audioPlay":false,"sceneViewState":{"showFog":true,"showMaterialUpdate":false,"showSkybox":false,"showFlares":true,"showImageEffects":true,"showParticleSystems":true},"in2DMode":false,"pivot":{"x":-0.12867483496665955,"y":-0.09029233455657959,"z":0.3764039874076843},"rotation":{"x":0.15716107189655305,"y":-0.0029665406327694656,"z":0.00048514571972191334,"w":0.9876095652580261},"size":0.328409343957901,"orthographic":false}