{"cameraMode":{"drawMode":0,"name":"Shaded","section":"Shading Mode"},"sceneLighting":false,"audioPlay":false,"sceneViewState":{"showFog":true,"showMaterialUpdate":false,"showSkybox":false,"showFlares":true,"showImageEffects":true,"showParticleSystems":true},"in2DMode":false,"pivot":{"x":0.05000000447034836,"y":0.05000000447034836,"z":0.05000000447034836},"rotation":{"x":-0.15863405168056489,"y":0.00947967916727066,"z":-0.001495912903919816,"w":-0.987319827079773},"size":0.11391080170869827,"orthographic":false}